jzhou_utils/__init__.py
jzhou_utils/base_utils.py
jzhou_utils/dt_utils.py
jzhou_utils/eval_utils.py
jzhou_utils/latex_utils.py
jzhou_utils/pd_utils.py
jzhou_utils/plot_utils.py
jzhou_utils/split_utils.py
jzhou_utils/algorithms/__init__.py
jzhou_utils/algorithms/highams.py
jzhou_utils/betting_utils/__init__.py
jzhou_utils/betting_utils/bet_conversion_utils.py
jzhou_utils/data_utils/__init__.py
jzhou_utils/data_utils/parquet_utils.py
jzhou_utils/data_utils/pdf_utils.py
jzhou_utils/data_utils/sql_utils.py
jzhou_utils/data_utils/.ipynb_checkpoints/__init__-checkpoint.py
jzhou_utils/data_utils/.ipynb_checkpoints/parquet_utils-checkpoint.py
jzhou_utils/data_utils/.ipynb_checkpoints/pdf_utils-checkpoint.py
jzhou_utils/data_utils/.ipynb_checkpoints/sql_utils-checkpoint.py
jzhou_utils-0.1.3.dist-info/METADATA
jzhou_utils-0.1.3.dist-info/WHEEL
jzhou_utils-0.1.3.dist-info/licenses/LICENSE
jzhou_utils-0.1.3.dist-info/RECORD
